mecher_amt_api_client/__init__.py
mecher_amt_api_client/amt_api_common.py
mecher_amt_api_client/client/__init__.py
mecher_amt_api_client/client/amt_api.py
mecher_amt_api_client/client/endpoints/__init__.py
mecher_amt_api_client/client/endpoints/app_artefact.py
mecher_amt_api_client/client/endpoints/app_run_config.py
mecher_amt_api_client/client/endpoints/auth.py
mecher_amt_api_client/client/endpoints/bs_owner.py
mecher_amt_api_client/models/__init__.py
mecher_amt_api_client/models/amt_user.py
mecher_amt_api_client/models/app_artefact.py
mecher_amt_api_client/models/app_run_config.py
mecher_amt_api_client/models/browserstack_owner.py
mecher_amt_api_client-0.0.9.dist-info/METADATA
mecher_amt_api_client-0.0.9.dist-info/WHEEL
mecher_amt_api_client-0.0.9.dist-info/top_level.txt
mecher_amt_api_client-0.0.9.dist-info/RECORD
